config_dir/__init__.py
config_dir-0.0.6.dist-info/LICENCE.md
config_dir-0.0.6.dist-info/METADATA
config_dir-0.0.6.dist-info/WHEEL
config_dir-0.0.6.dist-info/top_level.txt
config_dir-0.0.6.dist-info/RECORD
