Metadata-Version: 2.1
Name: config-dir
Version: 0.0.6
Summary: Configuration directory utilities
Home-page: https://github.com/jan-g/{name}
Author: jan grant 
Author-email: config-dir@ioctl.org
License: Apache License 2.0
Platform: UNKNOWN
Requires-Dist: pyyaml
